{
  "sections": {
    "main": {
      "type": "main-page",
      "settings": {
        "padding_top": 0,
        "padding_bottom": 0
      }
    },
    "1663787876e477e72f": {
      "type": "hero",
      "blocks": {
        "16637878765c503bf6-0": {
          "type": "eyebrow",
          "disabled": true,
          "settings": {
            "eyebrow": "<p>Eyebrow<\/p>"
          }
        },
        "16637878765c503bf6-1": {
          "type": "heading",
          "settings": {
            "heading": "Eagle Ray Awareness  Bracelets",
            "heading_size": "h1"
          }
        },
        "16637878765c503bf6-2": {
          "type": "copy",
          "settings": {
            "copy": "<p> <\/p>"
          }
        },
        "16637878765c503bf6-3": {
          "type": "button",
          "settings": {
            "text": "Shop Now",
            "link": "https:\/\/www.4ocean.com\/products\/eagle-ray-beaded-bracelet?variant=41925619876033"
          }
        }
      },
      "block_order": [
        "16637878765c503bf6-0",
        "16637878765c503bf6-1",
        "16637878765c503bf6-2",
        "16637878765c503bf6-3"
      ],
      "settings": {
        "desktop_content_alignment": "left",
        "overlay_opacity": 20,
        "video_url": "",
        "image": "shopify:\/\/shop_images\/Eagle-Ray-Module_3_085a73ca-83db-43fe-b474-60eda677316b.jpg"
      }
    },
    "16637895025d9f8778": {
      "type": "signature-bracelet",
      "blocks": {
        "16637895026abc2d5c-0": {
          "type": "icon",
          "settings": {
            "text": "",
            "visible_mobile": true
          }
        },
        "16637895026abc2d5c-1": {
          "type": "icon",
          "settings": {
            "text": "",
            "visible_mobile": true
          }
        },
        "16637895026abc2d5c-2": {
          "type": "icon",
          "settings": {
            "text": "",
            "visible_mobile": true
          }
        },
        "16637895026abc2d5c-3": {
          "type": "icon",
          "settings": {
            "text": "",
            "visible_mobile": true
          }
        },
        "16637895026abc2d5c-4": {
          "type": "icon",
          "settings": {
            "text": "",
            "visible_mobile": true
          }
        },
        "16637895026abc2d5c-5": {
          "type": "icon",
          "settings": {
            "text": "",
            "visible_mobile": true
          }
        }
      },
      "block_order": [
        "16637895026abc2d5c-0",
        "16637895026abc2d5c-1",
        "16637895026abc2d5c-2",
        "16637895026abc2d5c-3",
        "16637895026abc2d5c-4",
        "16637895026abc2d5c-5"
      ],
      "settings": {
        "pre_title": "",
        "title": "Beaded? Or braided? How will you pull your pound?",
        "description": "",
        "content_alignment": "center",
        "image": "shopify:\/\/shop_images\/Eagle-Ray-Module_2_e8f93c16-b5fd-424e-83cc-0fdf6f9108d5.gif",
        "product": "eagle-ray-beaded-bracelet",
        "atc_label": "Shop Now",
        "padding_top": 40,
        "padding_bottom": 52
      }
    },
    "166379140543369ed5": {
      "type": "image-with-text",
      "blocks": {
        "166379140529515825-0": {
          "type": "heading",
          "settings": {
            "heading": "Eagle Rays: Naturally Rare and Getting Rarer",
            "heading_size": "h1"
          }
        },
        "166379140529515825-1": {
          "type": "text",
          "settings": {
            "text": "<p>Pair text with an image to focus on your chosen product, collection, or blog post. Add details on availability, style, or even provide a review.<\/p>",
            "text_style": "body"
          }
        },
        "166379140529515825-2": {
          "type": "button",
          "settings": {
            "button_label": "Button label",
            "button_link": ""
          }
        }
      },
      "block_order": [
        "166379140529515825-0",
        "166379140529515825-1",
        "166379140529515825-2"
      ],
      "settings": {
        "height": "adapt",
        "desktop_image_width": "medium",
        "layout": "image_first",
        "desktop_content_position": "top",
        "desktop_content_alignment": "left",
        "content_layout": "no-overlap",
        "color_scheme": "background-1",
        "mobile_content_alignment": "left",
        "padding_top": 36,
        "padding_bottom": 36
      }
    }
  },
  "order": [
    "main",
    "1663787876e477e72f",
    "16637895025d9f8778",
    "166379140543369ed5"
  ]
}
