{
  "sections": {
    "main": {
      "type": "main-page",
      "disabled": true,
      "settings": {
        "padding_top": 28,
        "padding_bottom": 28
      }
    },
    "166299643560cb2626": {
      "type": "rich-text",
      "blocks": {
        "166299643504333830-0": {
          "type": "heading",
          "settings": {
            "heading": "<p>Careers<\/p>",
            "heading_size": "h1"
          }
        },
        "1d8fbe39-d56e-4fb0-bee0-c81528674a87": {
          "type": "caption",
          "settings": {
            "caption": "Check out our open positions:",
            "text_style": "subtitle",
            "text_size": "medium"
          }
        },
        "166299643504333830-1": {
          "type": "text",
          "settings": {
            "text": ""
          }
        },
        "166299643504333830-2": {
          "type": "button",
          "disabled": true,
          "settings": {
            "button_label": "Button label",
            "button_link": "",
            "button_style_secondary": false,
            "button_label_2": "",
            "button_link_2": "",
            "button_style_secondary_2": false
          }
        }
      },
      "block_order": [
        "166299643504333830-0",
        "1d8fbe39-d56e-4fb0-bee0-c81528674a87",
        "166299643504333830-1",
        "166299643504333830-2"
      ],
      "settings": {
        "desktop_content_position": "center",
        "content_alignment": "center",
        "color_scheme": "background-1",
        "full_width": true,
        "padding_top": 40,
        "padding_bottom": 52
      }
    }
  },
  "order": [
    "main",
    "166299643560cb2626"
  ]
}
